<?xml version="1.0" encoding="UTF-8"?>
<beans xmlns="http://www.springframework.org/schema/beans"
	xmlns:xsi="http://www.w3.org/2001/XMLSchema-instance"
	xmlns:mybatis-spring="http://mybatis.org/schema/mybatis-spring"
	xsi:schemaLocation="http://mybatis.org/schema/mybatis-spring http://mybatis.org/schema/mybatis-spring-1.2.xsd
		http://www.springframework.org/schema/beans https://www.springframework.org/schema/beans/spring-beans.xsd">
	
	<bean id="hikariConfig" class="com.zaxxer.hikari.HikariConfig">
		<property name="driverClassName" value="net.sf.log4jdbc.sql.jdbcapi.DriverSpy"></property>
		<property name="jdbcUrl" value="jdbc:log4jdbc:oracle:thin:@foodchoice_high?TNS_ADMIN=본인 경로 수정해서 올리기"></property>
		<property name="username" value="admin"></property>
		<property name="password" value="foodChoice231005"></property>
	</bean>	
	
	<bean id="dataSource" class="com.zaxxer.hikari.HikariDataSource" destroy-method="close">
		<constructor-arg ref="hikariConfig"></constructor-arg>		
	</bean>
	
	<bean id="sqlSessionFactory" class="org.mybatis.spring.SqlSessionFactoryBean">
		<property name="dataSource" ref="dataSource"></property>
		<property name="configLocation" value="classpath:/mybatis-config.xml"></property>
		<property name="mapperLocations" value="classpath:/com/foodchoice/food/mapper/*Mapper.xml"></property>
	</bean>
	<!-- MyBatis 연동에 사용될 객체들의 패키지 위치 지정(기본 루트 패키지 지정) -->
	<mybatis-spring:scan base-package="com.foodchoice.food" />
</beans>